aiguardrail/__init__.py
aiguardrail/guardrails.py
aiguardrail-0.1.0.dist-info/licenses/LICENSE
aiguardrail-0.1.0.dist-info/METADATA
aiguardrail-0.1.0.dist-info/WHEEL
aiguardrail-0.1.0.dist-info/top_level.txt
aiguardrail-0.1.0.dist-info/RECORD
