Metadata-Version: 2.4
Name: aiguardrail
Version: 0.1.0
Summary: Guardrails for evaluating AI-generated content
Author: Shubham Mhaske
Author-email: mhaskeshubham1200@gmail.com
Classifier: Programming Language :: Python :: 3
Classifier: Operating System :: OS Independent
Classifier: License :: OSI Approved :: MIT License
Requires-Python: >=3.7
License-File: LICENSE
Requires-Dist: pandas
Requires-Dist: tiktoken
Requires-Dist: detoxify
Requires-Dist: textstat
Dynamic: author
Dynamic: author-email
Dynamic: classifier
Dynamic: description
Dynamic: description-content-type
Dynamic: license-file
Dynamic: requires-dist
Dynamic: requires-python
Dynamic: summary
